odoo/addons/report_xlsx_helper/README.rst
odoo/addons/report_xlsx_helper/__init__.py
odoo/addons/report_xlsx_helper/__manifest__.py
odoo/addons/report_xlsx_helper/controllers/__init__.py
odoo/addons/report_xlsx_helper/controllers/main.py
odoo/addons/report_xlsx_helper/i18n/report_xlsx_helper.pot
odoo/addons/report_xlsx_helper/models/__init__.py
odoo/addons/report_xlsx_helper/models/ir_actions_report.py
odoo/addons/report_xlsx_helper/readme/CONTRIBUTORS.rst
odoo/addons/report_xlsx_helper/readme/DESCRIPTION.rst
odoo/addons/report_xlsx_helper/readme/INSTALL.rst
odoo/addons/report_xlsx_helper/readme/USAGE.rst
odoo/addons/report_xlsx_helper/report/__init__.py
odoo/addons/report_xlsx_helper/report/report_xlsx_abstract.py
odoo/addons/report_xlsx_helper/report/test_partner_report_xlsx.py
odoo/addons/report_xlsx_helper/static/description/icon.png
odoo/addons/report_xlsx_helper/static/description/index.html
odoo/addons/report_xlsx_helper/tests/__init__.py
odoo/addons/report_xlsx_helper/tests/test_report_xlsx_helper.py
odoo11_addon_report_xlsx_helper-11.0.1.0.0.99.dev5.dist-info/METADATA
odoo11_addon_report_xlsx_helper-11.0.1.0.0.99.dev5.dist-info/WHEEL
odoo11_addon_report_xlsx_helper-11.0.1.0.0.99.dev5.dist-info/top_level.txt
odoo11_addon_report_xlsx_helper-11.0.1.0.0.99.dev5.dist-info/RECORD
